mkdocs_platform_plugin/__init__.py
mkdocs_platform_plugin-0.1.2.dist-info/licenses/LICENSE
mkdocs_platform_plugin-0.1.2.dist-info/METADATA
mkdocs_platform_plugin-0.1.2.dist-info/WHEEL
mkdocs_platform_plugin-0.1.2.dist-info/entry_points.txt
mkdocs_platform_plugin-0.1.2.dist-info/top_level.txt
mkdocs_platform_plugin-0.1.2.dist-info/RECORD
