Metadata-Version: 2.4
Name: mkdocs-platform-plugin
Version: 0.1.2
Summary: MkDocs plugin to filter GitHub content-only and MkDocs website content-only.
Author-email: ralvarezdev <inquiries@ralvarez.dev>
License: MIT
Project-URL: Homepage, https://github.com/ralvarezdev/mkdocs-platform-plugin
Project-URL: Source, https://github.com/ralvarezdev/mkdocs-platform-plugin/klevor
Project-URL: Issues, https://github.com/ralvarezdev/mkdocs-platform-plugin/klevor/issues
Keywords: mkdocs,plugin,documentation,filter,content
Classifier: Development Status :: 3 - Alpha
Classifier: Intended Audience :: Developers
Classifier: License :: OSI Approved :: MIT License
Classifier: Programming Language :: Python
Classifier: Programming Language :: Python :: 3
Classifier: Programming Language :: Python :: 3 :: Only
Classifier: Programming Language :: Python :: 3.8
Classifier: Programming Language :: Python :: 3.9
Classifier: Programming Language :: Python :: 3.10
Classifier: Programming Language :: Python :: 3.11
Classifier: Programming Language :: Python :: 3.12
Classifier: Framework :: MkDocs
Classifier: Topic :: Documentation
Classifier: Topic :: Software Development :: Documentation
Requires-Python: >=3.8
License-File: LICENSE
Requires-Dist: mkdocs>=1.5
Dynamic: license-file
